simpleaudio/__init__.py
simpleaudio/_simpleaudio.cpython-37m-darwin.so
simpleaudio/functionchecks.py
simpleaudio/shiny.py
simpleaudio/test_audio/c.wav
simpleaudio/test_audio/e.wav
simpleaudio/test_audio/g.wav
simpleaudio/test_audio/left_right.wav
simpleaudio/test_audio/notes_2_16_44.wav
simpleaudio-1.0.3.dist-info/LICENSE.txt
simpleaudio-1.0.3.dist-info/METADATA
simpleaudio-1.0.3.dist-info/WHEEL
simpleaudio-1.0.3.dist-info/top_level.txt
simpleaudio-1.0.3.dist-info/RECORD
