Metadata-Version: 1.1
Name: simpleaudio
Version: 1.0.3
Summary: Simple, asynchronous audio playback for Python 3.
Home-page: https://github.com/hamiltron/py-simple-audio
Author: Joe Hamilton
Author-email: jhamilton10@georgefox.edu
License: MIT
Keywords: audio,wave,media,multimedia,sound,alsa,coreaudio,winmm,music
Platform: UNKNOWN
Classifier: License :: OSI Approved :: MIT License
Classifier: Programming Language :: Python :: 3.3
Classifier: Programming Language :: Python :: 3.4
Classifier: Programming Language :: Python :: 3.5
Classifier: Programming Language :: Python :: 3.6
Classifier: Topic :: Multimedia :: Sound/Audio
Classifier: Operating System :: POSIX :: Linux
Classifier: Operating System :: Microsoft :: Windows
Classifier: Operating System :: MacOS :: MacOS X
